{
  "schemaVersion": "1.0",
  "generatedAt": "2026-06-07T11:37:07Z",
  "entries": [
    {
      "id": "29er",
      "reason": "no assetUrl (not yet sourced)"
    },
    {
      "id": "49er",
      "reason": "no assetUrl (not yet sourced)"
    },
    {
      "id": "d2d",
      "reason": "no assetUrl (not yet sourced)"
    },
    {
      "id": "east-antrim-bc",
      "reason": "no assetUrl (not yet sourced)"
    },
    {
      "id": "idra-14",
      "reason": "no assetUrl (not yet sourced)"
    },
    {
      "id": "j80",
      "reason": "no assetUrl (not yet sourced)"
    },
    {
      "id": "mermaid",
      "reason": "no assetUrl (not yet sourced)"
    },
    {
      "id": "moth",
      "reason": "no assetUrl (not yet sourced)"
    },
    {
      "id": "royal-alfred-yc",
      "reason": "no assetUrl (not yet sourced)"
    },
    {
      "id": "sb20",
      "reason": "no assetUrl (not yet sourced)"
    },
    {
      "id": "sigma-33",
      "reason": "no assetUrl (not yet sourced)"
    },
    {
      "id": "water-wags",
      "reason": "no assetUrl (not yet sourced)"
    }
  ]
}
